<data>
  <brick elementID="241226" designID="2412" quantity="2"/>
  <brick elementID="302326" designID="3023" quantity="1"/>
  <brick elementID="317626" designID="3176" quantity="2"/>
  <brick elementID="4144533" designID="30540" quantity="4"/>
  <brick elementID="4167106" designID="30386" quantity="2"/>
  <brick elementID="6083074" designID="3300" quantity="1"/>
  <brick elementID="4158355" designID="3020" quantity="1"/>
  <brick elementID="4183047" designID="44301" quantity="2"/>
  <brick elementID="4190164" designID="2540" quantity="3"/>
  <brick elementID="4210699" designID="4735" quantity="1"/>
  <brick elementID="4210726" designID="30383" quantity="2"/>
  <brick elementID="3005741" designID="30057" quantity="2"/>
  <brick elementID="383901" designID="3839" quantity="2"/>
  <brick elementID="4179874" designID="43722" quantity="1"/>
  <brick elementID="4179875" designID="43723" quantity="1"/>
  <brick elementID="4538353" designID="61252" quantity="2"/>
  <brickCount acquired="29" totalInSet="29"/>
</data>
