<data>
  <brick elementID="9339" designID="73200" quantity="3"/>
  <brick elementID="265426" designID="2654" quantity="1"/>
  <brick elementID="306226" designID="3062" quantity="1"/>
  <brick elementID="362426" designID="3624" quantity="1"/>
  <brick elementID="379426" designID="3794" quantity="2"/>
  <brick elementID="383526" designID="3835" quantity="1"/>
  <brick elementID="407026" designID="4070" quantity="2"/>
  <brick elementID="460026" designID="4600" quantity="2"/>
  <brick elementID="614126" designID="6141" quantity="8"/>
  <brick elementID="4105175" designID="3878" quantity="1"/>
  <brick elementID="4216660" designID="30367" quantity="1"/>
  <brick elementID="4273590" designID="49668" quantity="1"/>
  <brick elementID="4275341" designID="76382" quantity="1"/>
  <brick elementID="4275401" designID="76382" quantity="1"/>
  <brick elementID="4508215" designID="30028" quantity="4"/>
  <brick elementID="4516843" designID="59895" quantity="2"/>
  <brick elementID="4517925" designID="61252" quantity="1"/>
  <brick elementID="4529236" designID="59900" quantity="1"/>
  <brick elementID="4121921" designID="3623" quantity="4"/>
  <brick elementID="9341" designID="73200" quantity="1"/>
  <brick elementID="243123" designID="2431" quantity="2"/>
  <brick elementID="302323" designID="3023" quantity="1"/>
  <brick elementID="403223" designID="4032" quantity="1"/>
  <brick elementID="4275813" designID="76382" quantity="1"/>
  <brick elementID="4296152" designID="73587" quantity="1"/>
  <brick elementID="4504380" designID="54200" quantity="1"/>
  <brick elementID="4567909" designID="86035" quantity="1"/>
  <brick elementID="4632567" designID="4081" quantity="1"/>
  <brick elementID="4120158" designID="73200" quantity="1"/>
  <brick elementID="4157103" designID="6141" quantity="1"/>
  <brick elementID="4210280" designID="3840" quantity="1"/>
  <brick elementID="4518029" designID="59900" quantity="5"/>
  <brick elementID="6031982" designID="76382" quantity="1"/>
  <brick elementID="9342" designID="73200" quantity="1"/>
  <brick elementID="9552" designID="73081" quantity="1"/>
  <brick elementID="74335" designID="73587" quantity="1"/>
  <brick elementID="243221" designID="2432" quantity="1"/>
  <brick elementID="254321" designID="2543" quantity="1"/>
  <brick elementID="306821" designID="3068" quantity="1"/>
  <brick elementID="379521" designID="3795" quantity="1"/>
  <brick elementID="383321" designID="3833" quantity="1"/>
  <brick elementID="389921" designID="3899" quantity="2"/>
  <brick elementID="4174747" designID="30133" quantity="2"/>
  <brick elementID="4220516" designID="47458" quantity="1"/>
  <brick elementID="4275872" designID="76382" quantity="1"/>
  <brick elementID="4275873" designID="76382" quantity="1"/>
  <brick elementID="4504379" designID="54200" quantity="5"/>
  <brick elementID="4521562" designID="76382" quantity="1"/>
  <brick elementID="4562544" designID="86035" quantity="1"/>
  <brick elementID="4588003" designID="60897" quantity="2"/>
  <brick elementID="4632572" designID="4081" quantity="3"/>
  <brick elementID="378824" designID="3788" quantity="1"/>
  <brick elementID="379424" designID="3794" quantity="2"/>
  <brick elementID="408324" designID="4083" quantity="1"/>
  <brick elementID="408524" designID="4085" quantity="2"/>
  <brick elementID="486524" designID="4865" quantity="2"/>
  <brick elementID="614124" designID="6141" quantity="3"/>
  <brick elementID="4116809" designID="83447" quantity="1"/>
  <brick elementID="4168995" designID="42523" quantity="1"/>
  <brick elementID="4194395" designID="45936" quantity="1"/>
  <brick elementID="4200908" designID="46506" quantity="1"/>
  <brick elementID="4261269" designID="51520" quantity="1"/>
  <brick elementID="4262093" designID="51519" quantity="1"/>
  <brick elementID="4289265" designID="44476" quantity="1"/>
  <brick elementID="4501232" designID="48336" quantity="1"/>
  <brick elementID="4506727" designID="59714" quantity="1"/>
  <brick elementID="4506998" designID="59716" quantity="1"/>
  <brick elementID="6030719" designID="12825" quantity="1"/>
  <brick elementID="6172120" designID="44674" quantity="1"/>
  <brick elementID="74040" designID="73200" quantity="1"/>
  <brick elementID="242328" designID="2423" quantity="1"/>
  <brick elementID="302328" designID="3023" quantity="2"/>
  <brick elementID="306928" designID="3069" quantity="2"/>
  <brick elementID="374128" designID="3741" quantity="1"/>
  <brick elementID="403228" designID="4032" quantity="1"/>
  <brick elementID="4106356" designID="3001" quantity="1"/>
  <brick elementID="4107637" designID="4286" quantity="8"/>
  <brick elementID="4121969" designID="3040" quantity="4"/>
  <brick elementID="4529239" designID="59900" quantity="1"/>
  <brick elementID="4529755" designID="62810" quantity="1"/>
  <brick elementID="4210698" designID="4349" quantity="1"/>
  <brick elementID="4210884" designID="44302" quantity="2"/>
  <brick elementID="4211001" designID="3710" quantity="1"/>
  <brick elementID="4211006" designID="3837" quantity="1"/>
  <brick elementID="4211043" designID="3021" quantity="1"/>
  <brick elementID="4211048" designID="6117" quantity="1"/>
  <brick elementID="4211065" designID="3020" quantity="1"/>
  <brick elementID="4211090" designID="3062" quantity="1"/>
  <brick elementID="4263176" designID="3839" quantity="1"/>
  <brick elementID="6081987" designID="18274" quantity="2"/>
  <brick elementID="4162916" designID="73200" quantity="1"/>
  <brick elementID="4530129" designID="41879" quantity="1"/>
  <brick elementID="4205058" designID="3001" quantity="1"/>
  <brick elementID="4288003" designID="76382" quantity="1"/>
  <brick elementID="4198316" designID="46303" quantity="2"/>
  <brick elementID="4211398" designID="3023" quantity="1"/>
  <brick elementID="4211464" designID="3839" quantity="2"/>
  <brick elementID="4211504" designID="4600" quantity="1"/>
  <brick elementID="4211506" designID="4624" quantity="2"/>
  <brick elementID="4211511" designID="4733" quantity="1"/>
  <brick elementID="4211803" designID="44301" quantity="2"/>
  <brick elementID="4514195" designID="60849" quantity="1"/>
  <brick elementID="6066097" designID="15573" quantity="1"/>
  <brick elementID="4211157" designID="3836" quantity="2"/>
  <brick elementID="4211159" designID="4032" quantity="2"/>
  <brick elementID="4211183" designID="3062" quantity="5"/>
  <brick elementID="4211185" designID="30150" quantity="1"/>
  <brick elementID="4211204" designID="6636" quantity="3"/>
  <brick elementID="4211210" designID="3003" quantity="1"/>
  <brick elementID="4221590" designID="3666" quantity="1"/>
  <brick elementID="4495724" designID="4523" quantity="1"/>
  <brick elementID="6121728" designID="61976" quantity="1"/>
  <brick elementID="4113949" designID="30151" quantity="1"/>
  <brick elementID="3005743" designID="30057" quantity="2"/>
  <brick elementID="3006843" designID="30068" quantity="2"/>
  <brick elementID="4244366" designID="50746" quantity="1"/>
  <brick elementID="4567331" designID="64288" quantity="1"/>
  <brick elementID="4222960" designID="30057" quantity="2"/>
  <brick elementID="4567338" designID="64288" quantity="1"/>
  <brick elementID="4244368" designID="50746" quantity="1"/>
  <brick elementID="4218642" designID="6124" quantity="1"/>
  <brick elementID="3005748" designID="30057" quantity="1"/>
  <brick elementID="4155537" designID="6126" quantity="1"/>
  <brick elementID="3005741" designID="30057" quantity="1"/>
  <brick elementID="287701" designID="2877" quantity="2"/>
  <brick elementID="300501" designID="3005" quantity="2"/>
  <brick elementID="302001" designID="3020" quantity="2"/>
  <brick elementID="302101" designID="3021" quantity="1"/>
  <brick elementID="302201" designID="3022" quantity="1"/>
  <brick elementID="302301" designID="3023" quantity="6"/>
  <brick elementID="362601" designID="3626" quantity="1"/>
  <brick elementID="371001" designID="3710" quantity="1"/>
  <brick elementID="379401" designID="3794" quantity="1"/>
  <brick elementID="390001" designID="3900" quantity="2"/>
  <brick elementID="395701" designID="3957" quantity="4"/>
  <brick elementID="403201" designID="4032" quantity="1"/>
  <brick elementID="407001" designID="4070" quantity="2"/>
  <brick elementID="408501" designID="4085" quantity="2"/>
  <brick elementID="474001" designID="4740" quantity="1"/>
  <brick elementID="613201" designID="6132" quantity="1"/>
  <brick elementID="614101" designID="6141" quantity="7"/>
  <brick elementID="3002701" designID="30027" quantity="4"/>
  <brick elementID="4119410" designID="83608" quantity="1"/>
  <brick elementID="4121932" designID="3040" quantity="4"/>
  <brick elementID="4129836" designID="30374" quantity="1"/>
  <brick elementID="4143254" designID="30414" quantity="1"/>
  <brick elementID="4179580" designID="43898" quantity="2"/>
  <brick elementID="4186952" designID="3742" quantity="1"/>
  <brick elementID="4212379" designID="47893" quantity="1"/>
  <brick elementID="4224792" designID="49668" quantity="4"/>
  <brick elementID="4249741" designID="3898" quantity="1"/>
  <brick elementID="4275461" designID="76382" quantity="1"/>
  <brick elementID="4277926" designID="44728" quantity="1"/>
  <brick elementID="4504369" designID="54200" quantity="2"/>
  <brick elementID="4632566" designID="4081" quantity="2"/>
  <brick elementID="6011986" designID="81267" quantity="1"/>
  <brick elementID="6108662" designID="3943" quantity="1"/>
  <brickCount acquired="256" totalInSet="257"/>
</data>
