<data>
  <brick elementID="73667" designID="73587" quantity="1"/>
  <brick elementID="300326" designID="3003" quantity="2"/>
  <brick elementID="614126" designID="6141" quantity="2"/>
  <brick elementID="4143372" designID="30553" quantity="1"/>
  <brick elementID="4109810" designID="32062" quantity="4"/>
  <brick elementID="4206482" designID="43093" quantity="1"/>
  <brick elementID="302324" designID="3023" quantity="1"/>
  <brick elementID="379527" designID="3795" quantity="3"/>
  <brick elementID="474027" designID="4740" quantity="2"/>
  <brick elementID="3000027" designID="30000" quantity="1"/>
  <brick elementID="4124056" designID="2412" quantity="1"/>
  <brick elementID="4144501" designID="30365" quantity="4"/>
  <brick elementID="4192271" designID="30602" quantity="1"/>
  <brick elementID="73588" designID="73587" quantity="4"/>
  <brick elementID="241202" designID="2412" quantity="2"/>
  <brick elementID="302002" designID="3020" quantity="3"/>
  <brick elementID="302302" designID="3023" quantity="7"/>
  <brick elementID="303102" designID="3031" quantity="1"/>
  <brick elementID="370002" designID="3700" quantity="1"/>
  <brick elementID="379402" designID="3794" quantity="1"/>
  <brick elementID="408102" designID="4081" quantity="1"/>
  <brick elementID="3200002" designID="32000" quantity="1"/>
  <brick elementID="4142966" designID="30554" quantity="8"/>
  <brick elementID="4143752" designID="30552" quantity="4"/>
  <brick elementID="4185590" designID="44567" quantity="1"/>
  <brick elementID="4167842" designID="6225" quantity="1"/>
  <brick elementID="306901" designID="3069" quantity="1"/>
  <brick elementID="379401" designID="3794" quantity="2"/>
  <brick elementID="614101" designID="6141" quantity="1"/>
  <brick elementID="4160857" designID="41769" quantity="1"/>
  <brick elementID="4161326" designID="41770" quantity="1"/>
  <brickCount acquired="65" totalInSet="98"/>
</data>
