<data>
  <brick elementID="244126" designID="2441" quantity="1"/>
  <brick elementID="249626" designID="2496" quantity="1"/>
  <brick elementID="4124096" designID="6134" quantity="2"/>
  <brick elementID="4508215" designID="30028" quantity="5"/>
  <brick elementID="4535739" designID="63868" quantity="2"/>
  <brick elementID="4568644" designID="87697" quantity="4"/>
  <brick elementID="4613153" designID="93273" quantity="3"/>
  <brick elementID="6070695" designID="14769" quantity="1"/>
  <brick elementID="6092658" designID="10313" quantity="4"/>
  <brick elementID="6114987" designID="11458" quantity="2"/>
  <brick elementID="6139403" designID="98138" quantity="1"/>
  <brick elementID="4121715" designID="2780" quantity="4"/>
  <brick elementID="4552347" designID="60484" quantity="2"/>
  <brick elementID="4113233" designID="3710" quantity="2"/>
  <brick elementID="4113916" designID="3010" quantity="3"/>
  <brick elementID="4243824" designID="3031" quantity="1"/>
  <brick elementID="4514554" designID="32556" quantity="1"/>
  <brick elementID="4514553" designID="6558" quantity="1"/>
  <brick elementID="6056261" designID="87079" quantity="2"/>
  <brick elementID="6057387" designID="3023" quantity="1"/>
  <brick elementID="6097094" designID="3666" quantity="1"/>
  <brick elementID="6127601" designID="54200" quantity="2"/>
  <brick elementID="6132918" designID="11477" quantity="2"/>
  <brick elementID="6209679" designID="24866" quantity="1"/>
  <brick elementID="6222189" designID="15068" quantity="2"/>
  <brick elementID="6224170" designID="36293" quantity="1"/>
  <brick elementID="306221" designID="3062" quantity="1"/>
  <brick elementID="459921" designID="4599" quantity="1"/>
  <brick elementID="6101073" designID="15573" quantity="2"/>
  <brick elementID="6142402" designID="24201" quantity="2"/>
  <brick elementID="6248482" designID="35391" quantity="2"/>
  <brick elementID="6092592" designID="15573" quantity="1"/>
  <brick elementID="6147274" designID="3034" quantity="1"/>
  <brick elementID="6061201" designID="3069" quantity="3"/>
  <brick elementID="6147726" designID="11477" quantity="4"/>
  <brick elementID="6201647" designID="3023" quantity="3"/>
  <brick elementID="4640891" designID="3795" quantity="3"/>
  <brick elementID="6031839" designID="93606" quantity="2"/>
  <brick elementID="6092667" designID="15207" quantity="6"/>
  <brick elementID="6133838" designID="54200" quantity="2"/>
  <brick elementID="6137300" designID="11477" quantity="2"/>
  <brick elementID="6151657" designID="3666" quantity="2"/>
  <brick elementID="6151659" designID="3069" quantity="1"/>
  <brick elementID="6151663" designID="85984" quantity="3"/>
  <brick elementID="6151664" designID="3024" quantity="2"/>
  <brick elementID="6151669" designID="6091" quantity="4"/>
  <brick elementID="6153538" designID="3623" quantity="4"/>
  <brick elementID="6224991" designID="93604" quantity="1"/>
  <brick elementID="6133569" designID="24604" quantity="1"/>
  <brick elementID="4210631" designID="2412" quantity="1"/>
  <brick elementID="4210698" designID="4349" quantity="2"/>
  <brick elementID="4211001" designID="3710" quantity="3"/>
  <brick elementID="4211051" designID="30162" quantity="1"/>
  <brick elementID="4211065" designID="3020" quantity="3"/>
  <brick elementID="4521187" designID="60478" quantity="2"/>
  <brick elementID="6115080" designID="18674" quantity="1"/>
  <brick elementID="4184108" designID="3024" quantity="2"/>
  <brick elementID="4502089" designID="3710" quantity="1"/>
  <brick elementID="4504374" designID="54200" quantity="2"/>
  <brick elementID="4528482" designID="2420" quantity="2"/>
  <brick elementID="4528981" designID="3023" quantity="5"/>
  <brick elementID="4530028" designID="3021" quantity="2"/>
  <brick elementID="4565320" designID="87580" quantity="3"/>
  <brick elementID="6003573" designID="52031" quantity="1"/>
  <brick elementID="4211350" designID="2412" quantity="1"/>
  <brick elementID="4211397" designID="3022" quantity="3"/>
  <brick elementID="4211398" designID="3023" quantity="2"/>
  <brick elementID="4211469" designID="3937" quantity="2"/>
  <brick elementID="4211473" designID="3957" quantity="1"/>
  <brick elementID="4211474" designID="3958" quantity="1"/>
  <brick elementID="4211524" designID="6140" quantity="1"/>
  <brick elementID="4211525" designID="6141" quantity="2"/>
  <brick elementID="4211636" designID="30414" quantity="1"/>
  <brick elementID="4211764" designID="6014" quantity="4"/>
  <brick elementID="4221775" designID="73587" quantity="2"/>
  <brick elementID="4226995" designID="73081" quantity="1"/>
  <brick elementID="4541978" designID="61252" quantity="6"/>
  <brick elementID="4644102" designID="98397" quantity="1"/>
  <brick elementID="4654582" designID="99781" quantity="2"/>
  <brick elementID="4662161" designID="91988" quantity="1"/>
  <brick elementID="6044706" designID="14682" quantity="2"/>
  <brick elementID="6066097" designID="15573" quantity="2"/>
  <brick elementID="6071229" designID="15712" quantity="1"/>
  <brick elementID="6146223" designID="26169" quantity="1"/>
  <brick elementID="6152344" designID="26716" quantity="1"/>
  <brick elementID="6168647" designID="28626" quantity="1"/>
  <brick elementID="4211508" designID="4697" quantity="1"/>
  <brick elementID="4211668" designID="32348" quantity="2"/>
  <brick elementID="6218897" designID="37588" quantity="1"/>
  <brick elementID="6224889" designID="92456" quantity="1"/>
  <brick elementID="6103444" designID="11402" quantity="1"/>
  <brick elementID="6244787" designID="35334" quantity="1"/>
  <brick elementID="6254638" designID="39889" quantity="1"/>
  <brick elementID="6171764" designID="28624" quantity="1"/>
  <brick elementID="6022171" designID="98138" quantity="1"/>
  <brick elementID="6240230" designID="34823" quantity="4"/>
  <brick elementID="6240216" designID="34823" quantity="2"/>
  <brick elementID="300101" designID="3001" quantity="1"/>
  <brick elementID="300401" designID="3004" quantity="2"/>
  <brick elementID="303201" designID="3032" quantity="1"/>
  <brick elementID="362301" designID="3623" quantity="4"/>
  <brick elementID="366501" designID="3665" quantity="4"/>
  <brick elementID="366601" designID="3666" quantity="1"/>
  <brick elementID="379501" designID="3795" quantity="2"/>
  <brick elementID="614101" designID="6141" quantity="1"/>
  <brick elementID="654101" designID="6541" quantity="4"/>
  <brick elementID="4111971" designID="4733" quantity="1"/>
  <brick elementID="4116816" designID="30261" quantity="1"/>
  <brick elementID="4222017" designID="48336" quantity="2"/>
  <brick elementID="4243812" designID="3031" quantity="1"/>
  <brick elementID="4259940" designID="50745" quantity="2"/>
  <brick elementID="4518400" designID="59900" quantity="2"/>
  <brick elementID="4528341" designID="3033" quantity="1"/>
  <brick elementID="4530590" designID="60594" quantity="1"/>
  <brick elementID="4547489" designID="85984" quantity="2"/>
  <brick elementID="4613256" designID="60897" quantity="6"/>
  <brick elementID="6011380" designID="74967" quantity="4"/>
  <brick elementID="6023806" designID="93273" quantity="4"/>
  <brick elementID="6047220" designID="15068" quantity="1"/>
  <brick elementID="6055541" designID="14716" quantity="2"/>
  <brick elementID="6070698" designID="99780" quantity="2"/>
  <brick elementID="6093479" designID="18971" quantity="2"/>
  <brick elementID="6248283" designID="35573" quantity="1"/>
  <brickCount acquired="246" totalInSet="247"/>
</data>
