<data>
  <brick elementID="73081" designID="73081" quantity="1"/>
  <brick elementID="243126" designID="2431" quantity="2"/>
  <brick elementID="243626" designID="2436" quantity="2"/>
  <brick elementID="300126" designID="3001" quantity="2"/>
  <brick elementID="300326" designID="3003" quantity="4"/>
  <brick elementID="300426" designID="3004" quantity="7"/>
  <brick elementID="300926" designID="3009" quantity="3"/>
  <brick elementID="301026" designID="3010" quantity="1"/>
  <brick elementID="302326" designID="3023" quantity="8"/>
  <brick elementID="371026" designID="3710" quantity="4"/>
  <brick elementID="374726" designID="3747" quantity="1"/>
  <brick elementID="379426" designID="3794" quantity="3"/>
  <brick elementID="449726" designID="4497" quantity="1"/>
  <brick elementID="459926" designID="4599" quantity="2"/>
  <brick elementID="3004626" designID="30046" quantity="1"/>
  <brick elementID="4118624" designID="30237" quantity="1"/>
  <brick elementID="4183060" designID="44302" quantity="2"/>
  <brick elementID="4191191" designID="45677" quantity="1"/>
  <brick elementID="4213374" designID="47455" quantity="4"/>
  <brick elementID="4219107" designID="47753" quantity="1"/>
  <brick elementID="4273590" designID="49668" quantity="18"/>
  <brick elementID="4273703" designID="3678" quantity="2"/>
  <brick elementID="4504382" designID="54200" quantity="6"/>
  <brick elementID="4515373" designID="60481" quantity="12"/>
  <brick elementID="4526110" designID="62810" quantity="1"/>
  <brick elementID="4541455" designID="61254" quantity="4"/>
  <brick elementID="4550017" designID="60897" quantity="2"/>
  <brick elementID="4556158" designID="60470" quantity="2"/>
  <brick elementID="4558954" designID="87087" quantity="6"/>
  <brick elementID="4613404" designID="90462" quantity="2"/>
  <brick elementID="6040297" designID="43710" quantity="1"/>
  <brick elementID="6040298" designID="43711" quantity="1"/>
  <brick elementID="4290713" designID="32474" quantity="1"/>
  <brick elementID="4109995" designID="3004" quantity="6"/>
  <brick elementID="4112982" designID="3009" quantity="2"/>
  <brick elementID="4113233" designID="3710" quantity="4"/>
  <brick elementID="4113916" designID="3010" quantity="1"/>
  <brick elementID="4113988" designID="3034" quantity="1"/>
  <brick elementID="4114064" designID="2454" quantity="4"/>
  <brick elementID="4114077" designID="2420" quantity="2"/>
  <brick elementID="4114084" designID="3022" quantity="4"/>
  <brick elementID="4114306" designID="3003" quantity="14"/>
  <brick elementID="4114322" designID="3039" quantity="5"/>
  <brick elementID="4117070" designID="3062" quantity="12"/>
  <brick elementID="4118790" designID="3021" quantity="22"/>
  <brick elementID="4121921" designID="3623" quantity="8"/>
  <brick elementID="4124460" designID="4865" quantity="4"/>
  <brick elementID="4141533" designID="3007" quantity="4"/>
  <brick elementID="4157277" designID="6636" quantity="6"/>
  <brick elementID="4159739" designID="3002" quantity="12"/>
  <brick elementID="4181134" designID="44237" quantity="4"/>
  <brick elementID="4185177" designID="3068" quantity="3"/>
  <brick elementID="4212560" designID="30363" quantity="7"/>
  <brick elementID="4243911" designID="30249" quantity="4"/>
  <brick elementID="4249019" designID="3832" quantity="1"/>
  <brick elementID="6122047" designID="87079" quantity="4"/>
  <brick elementID="302321" designID="3023" quantity="2"/>
  <brick elementID="4538780" designID="64728" quantity="1"/>
  <brick elementID="301024" designID="3010" quantity="2"/>
  <brick elementID="614124" designID="6141" quantity="4"/>
  <brick elementID="4141630" designID="32028" quantity="4"/>
  <brick elementID="4181143" designID="44237" quantity="1"/>
  <brick elementID="4613411" designID="94061" quantity="1"/>
  <brick elementID="6030719" designID="12825" quantity="2"/>
  <brick elementID="4613755" designID="76382" quantity="1"/>
  <brick elementID="4114348" designID="30176" quantity="4"/>
  <brick elementID="4615606" designID="3022" quantity="8"/>
  <brick elementID="4210724" designID="30365" quantity="16"/>
  <brick elementID="4211007" designID="3841" quantity="1"/>
  <brick elementID="4211042" designID="4032" quantity="4"/>
  <brick elementID="4211043" designID="3021" quantity="3"/>
  <brick elementID="4211065" designID="3020" quantity="11"/>
  <brick elementID="4211067" designID="2445" quantity="1"/>
  <brick elementID="4211115" designID="3032" quantity="2"/>
  <brick elementID="4225973" designID="48169" quantity="4"/>
  <brick elementID="4227395" designID="48170" quantity="4"/>
  <brick elementID="4504378" designID="54200" quantity="2"/>
  <brick elementID="4523773" designID="30141" quantity="1"/>
  <brick elementID="4558955" designID="87087" quantity="2"/>
  <brick elementID="4499858" designID="55013" quantity="1"/>
  <brick elementID="4153653" designID="3039" quantity="3"/>
  <brick elementID="4177741" designID="3062" quantity="6"/>
  <brick elementID="4186627" designID="3794" quantity="6"/>
  <brick elementID="4196736" designID="3045" quantity="4"/>
  <brick elementID="4296785" designID="3003" quantity="4"/>
  <brick elementID="4578094" designID="3037" quantity="3"/>
  <brick elementID="6103405" designID="3040" quantity="2"/>
  <brick elementID="4211350" designID="2412" quantity="1"/>
  <brick elementID="4211369" designID="2555" quantity="2"/>
  <brick elementID="4211393" designID="3009" quantity="4"/>
  <brick elementID="4211415" designID="3070" quantity="2"/>
  <brick elementID="4211440" designID="3700" quantity="2"/>
  <brick elementID="4211486" designID="4282" quantity="2"/>
  <brick elementID="4211613" designID="2653" quantity="2"/>
  <brick elementID="4211636" designID="30414" quantity="2"/>
  <brick elementID="4211693" designID="30364" quantity="8"/>
  <brick elementID="4211803" designID="44301" quantity="10"/>
  <brick elementID="4494475" designID="47457" quantity="1"/>
  <brick elementID="4499259" designID="56902" quantity="4"/>
  <brick elementID="4523353" designID="30044" quantity="1"/>
  <brick elementID="4529120" designID="47720" quantity="2"/>
  <brick elementID="4558169" designID="63864" quantity="4"/>
  <brick elementID="4595836" designID="86208" quantity="2"/>
  <brick elementID="4613425" designID="94065" quantity="2"/>
  <brick elementID="4613454" designID="76382" quantity="2"/>
  <brick elementID="4613494" designID="94082" quantity="2"/>
  <brick elementID="6117967" designID="21712" quantity="4"/>
  <brick elementID="4224301" designID="3045" quantity="4"/>
  <brick elementID="4276180" designID="2449" quantity="2"/>
  <brick elementID="4539082" designID="6091" quantity="2"/>
  <brick elementID="4541380" designID="3037" quantity="1"/>
  <brick elementID="4541526" designID="3040" quantity="8"/>
  <brick elementID="4549992" designID="85975" quantity="2"/>
  <brick elementID="4585630" designID="3747" quantity="6"/>
  <brick elementID="4613269" designID="30149" quantity="1"/>
  <brick elementID="4613761" designID="87580" quantity="2"/>
  <brick elementID="6028713" designID="92903" quantity="4"/>
  <brick elementID="4251796" designID="3036" quantity="3"/>
  <brick elementID="4255416" designID="3003" quantity="2"/>
  <brick elementID="4507045" designID="3068" quantity="2"/>
  <brick elementID="4521914" designID="3004" quantity="16"/>
  <brick elementID="4524098" designID="73200" quantity="1"/>
  <brick elementID="4528604" designID="3023" quantity="10"/>
  <brick elementID="4530678" designID="3040" quantity="10"/>
  <brick elementID="4550329" designID="3795" quantity="5"/>
  <brick elementID="6000852" designID="98560" quantity="4"/>
  <brick elementID="4610904" designID="93247" quantity="1"/>
  <brick elementID="3005740" designID="30057" quantity="2"/>
  <brick elementID="6054554" designID="15714" quantity="1"/>
  <brick elementID="3005741" designID="30057" quantity="10"/>
  <brick elementID="4295174" designID="3048" quantity="4"/>
  <brick elementID="4529247" designID="59900" quantity="2"/>
  <brick elementID="4557385" designID="30169" quantity="2"/>
  <brick elementID="4585493" designID="48336" quantity="2"/>
  <brick elementID="4587002" designID="54200" quantity="2"/>
  <brick elementID="4610763" designID="93247" quantity="1"/>
  <brickCount acquired="524" totalInSet="527"/>
</data>
