<data>
  <brick elementID="4556158" designID="60470" quantity="4"/>
  <brick elementID="6015891" designID="11090" quantity="4"/>
  <brick elementID="6167800" designID="28620" quantity="6"/>
  <brick elementID="302223" designID="3022" quantity="4"/>
  <brick elementID="4278276" designID="2654" quantity="1"/>
  <brick elementID="4613257" designID="60897" quantity="8"/>
  <brick elementID="6055065" designID="11477" quantity="4"/>
  <brick elementID="6163471" designID="99781" quantity="8"/>
  <brick elementID="6251183" designID="76382" quantity="1"/>
  <brick elementID="6251186" designID="44940" quantity="1"/>
  <brick elementID="302324" designID="3023" quantity="4"/>
  <brick elementID="6167223" designID="24201" quantity="4"/>
  <brick elementID="6179329" designID="11476" quantity="4"/>
  <brick elementID="6191858" designID="33849" quantity="1"/>
  <brick elementID="6270099" designID="87747" quantity="4"/>
  <brick elementID="6250871" designID="40925" quantity="1"/>
  <brick elementID="6250926" designID="40923" quantity="1"/>
  <brick elementID="6116593" designID="21459" quantity="1"/>
  <brick elementID="6170290" designID="28623" quantity="8"/>
  <brick elementID="6245280" designID="35338" quantity="8"/>
  <brick elementID="6211795" designID="27256" quantity="4"/>
  <brick elementID="4585493" designID="48336" quantity="12"/>
  <brick elementID="6212965" designID="36648" quantity="4"/>
  <brickCount acquired="97" totalInSet="97"/>
</data>
