<data>
  <brick elementID="249626" designID="2496" quantity="1"/>
  <brick elementID="371026" designID="3710" quantity="1"/>
  <brick elementID="434926" designID="4349" quantity="1"/>
  <brick elementID="474026" designID="4740" quantity="1"/>
  <brick elementID="4568644" designID="87697" quantity="4"/>
  <brick elementID="4613153" designID="93273" quantity="1"/>
  <brick elementID="6023257" designID="30076" quantity="1"/>
  <brick elementID="6025012" designID="12622" quantity="1"/>
  <brick elementID="6053077" designID="15068" quantity="1"/>
  <brick elementID="6057397" designID="16091" quantity="1"/>
  <brick elementID="6179660" designID="31584" quantity="1"/>
  <brick elementID="6223058" designID="38131" quantity="1"/>
  <brick elementID="4121715" designID="2780" quantity="2"/>
  <brick elementID="4114322" designID="3039" quantity="2"/>
  <brick elementID="6217703" designID="24791" quantity="1"/>
  <brick elementID="6223192" designID="15624" quantity="1"/>
  <brick elementID="306223" designID="3062" quantity="1"/>
  <brick elementID="243221" designID="2432" quantity="1"/>
  <brick elementID="302221" designID="3022" quantity="1"/>
  <brick elementID="4216657" designID="30367" quantity="1"/>
  <brick elementID="4261628" designID="4345" quantity="1"/>
  <brick elementID="4558886" designID="87087" quantity="1"/>
  <brick elementID="6019155" designID="11211" quantity="2"/>
  <brick elementID="6066342" designID="14769" quantity="1"/>
  <brick elementID="6126048" designID="23893" quantity="4"/>
  <brick elementID="6224983" designID="38448" quantity="2"/>
  <brick elementID="6226654" designID="16360" quantity="1"/>
  <brick elementID="6226656" designID="16360" quantity="1"/>
  <brick elementID="6242131" designID="31496" quantity="1"/>
  <brick elementID="9553" designID="73081" quantity="1"/>
  <brick elementID="245824" designID="2458" quantity="2"/>
  <brick elementID="6133728" designID="3710" quantity="3"/>
  <brick elementID="6211448" designID="40244" quantity="2"/>
  <brick elementID="6223039" designID="3666" quantity="2"/>
  <brick elementID="6223279" designID="38190" quantity="1"/>
  <brick elementID="4295260" designID="82317" quantity="3"/>
  <brick elementID="6171069" designID="28967" quantity="1"/>
  <brick elementID="6223040" designID="3010" quantity="4"/>
  <brick elementID="4520307" designID="61780" quantity="1"/>
  <brick elementID="4540386" designID="61409" quantity="2"/>
  <brick elementID="4543086" designID="32028" quantity="1"/>
  <brick elementID="4598769" designID="92593" quantity="1"/>
  <brick elementID="6000311" designID="98283" quantity="2"/>
  <brick elementID="6055310" designID="15533" quantity="2"/>
  <brick elementID="6071261" designID="15068" quantity="2"/>
  <brick elementID="6126083" designID="23893" quantity="2"/>
  <brick elementID="6134910" designID="24741" quantity="1"/>
  <brick elementID="6222527" designID="38069" quantity="1"/>
  <brick elementID="6222794" designID="38075" quantity="1"/>
  <brick elementID="6223134" designID="38156" quantity="1"/>
  <brick elementID="6076674" designID="17833" quantity="1"/>
  <brick elementID="6223248" designID="76382" quantity="1"/>
  <brick elementID="4211387" designID="3003" quantity="1"/>
  <brick elementID="4211407" designID="3035" quantity="1"/>
  <brick elementID="4211410" designID="3039" quantity="1"/>
  <brick elementID="4211445" designID="3710" quantity="2"/>
  <brick elementID="4211764" designID="6014" quantity="4"/>
  <brick elementID="4228198" designID="50344" quantity="1"/>
  <brick elementID="4599498" designID="92593" quantity="1"/>
  <brick elementID="6028324" designID="98100" quantity="1"/>
  <brick elementID="6092111" designID="61409" quantity="2"/>
  <brick elementID="6105964" designID="18980" quantity="1"/>
  <brick elementID="6106189" designID="15254" quantity="1"/>
  <brick elementID="6123809" designID="22885" quantity="1"/>
  <brick elementID="6129340" designID="18653" quantity="2"/>
  <brick elementID="6223055" designID="38122" quantity="1"/>
  <brick elementID="6223082" designID="38138" quantity="1"/>
  <brick elementID="4216625" designID="3298" quantity="2"/>
  <brick elementID="4270443" designID="41879" quantity="1"/>
  <brick elementID="4626666" designID="47759" quantity="2"/>
  <brick elementID="6078605" designID="33183" quantity="1"/>
  <brick elementID="6210762" designID="36268" quantity="1"/>
  <brick elementID="6075617" designID="98283" quantity="6"/>
  <brick elementID="6075621" designID="2454" quantity="2"/>
  <brick elementID="4660846" designID="98289" quantity="1"/>
  <brick elementID="6037408" designID="11092" quantity="2"/>
  <brick elementID="6117400" designID="21610" quantity="1"/>
  <brick elementID="4609774" designID="64713" quantity="2"/>
  <brick elementID="6124924" designID="6118" quantity="4"/>
  <brick elementID="6247357" designID="35401" quantity="1"/>
  <brick elementID="6167741" designID="28618" quantity="1"/>
  <brick elementID="6167739" designID="28618" quantity="1"/>
  <brick elementID="6247792" designID="28556" quantity="1"/>
  <brick elementID="6253361" designID="35243" quantity="1"/>
  <brick elementID="6251290" designID="35386" quantity="3"/>
  <brick elementID="6238674" designID="35390" quantity="1"/>
  <brick elementID="6240216" designID="34823" quantity="1"/>
  <brick elementID="6107197" designID="3069" quantity="2"/>
  <brick elementID="6107209" designID="43888" quantity="2"/>
  <brick elementID="6174085" designID="29377" quantity="1"/>
  <brick elementID="300301" designID="3003" quantity="1"/>
  <brick elementID="371001" designID="3710" quantity="1"/>
  <brick elementID="379401" designID="3794" quantity="1"/>
  <brick elementID="4143000" designID="30363" quantity="2"/>
  <brick elementID="4547489" designID="85984" quantity="1"/>
  <brick elementID="6046905" designID="15070" quantity="2"/>
  <brick elementID="6052201" designID="80269" quantity="1"/>
  <brick elementID="6170709" designID="28980" quantity="1"/>
  <brick elementID="6225227" designID="27063" quantity="1"/>
  <brickCount acquired="149" totalInSet="149"/>
</data>
