<data>
  <brick elementID="302326" designID="3023" quantity="2"/>
  <brick elementID="4613759" designID="92582" quantity="1"/>
  <brick elementID="6020193" designID="99780" quantity="6"/>
  <brick elementID="6053077" designID="15068" quantity="1"/>
  <brick elementID="6061032" designID="10247" quantity="4"/>
  <brick elementID="6102734" designID="15403" quantity="2"/>
  <brick elementID="6122096" designID="21778" quantity="1"/>
  <brick elementID="6147050" designID="24201" quantity="2"/>
  <brick elementID="6168620" designID="28802" quantity="2"/>
  <brick elementID="6198993" designID="76382" quantity="1"/>
  <brick elementID="4121715" designID="2780" quantity="2"/>
  <brick elementID="6117748" designID="30602" quantity="2"/>
  <brick elementID="4164037" designID="3023" quantity="5"/>
  <brick elementID="302028" designID="3020" quantity="2"/>
  <brick elementID="303428" designID="3034" quantity="1"/>
  <brick elementID="4157120" designID="2420" quantity="2"/>
  <brick elementID="6021539" designID="93273" quantity="1"/>
  <brick elementID="6042951" designID="11153" quantity="2"/>
  <brick elementID="6170764" designID="62361" quantity="2"/>
  <brick elementID="6179681" designID="31584" quantity="1"/>
  <brick elementID="6199002" designID="34843" quantity="1"/>
  <brick elementID="6250600" designID="35399" quantity="4"/>
  <brick elementID="4210726" designID="30383" quantity="2"/>
  <brick elementID="6051334" designID="15392" quantity="2"/>
  <brick elementID="4211397" designID="3022" quantity="2"/>
  <brick elementID="4211445" designID="3710" quantity="2"/>
  <brick elementID="4211476" designID="4070" quantity="2"/>
  <brick elementID="4598526" designID="92280" quantity="2"/>
  <brick elementID="6092111" designID="61409" quantity="2"/>
  <brick elementID="6144138" designID="24201" quantity="2"/>
  <brick elementID="6198988" designID="34837" quantity="1"/>
  <brick elementID="6163901" designID="28558" quantity="2"/>
  <brick elementID="6254267" designID="35345" quantity="1"/>
  <brick elementID="6096717" designID="18989" quantity="2"/>
  <brick elementID="6154308" designID="48169" quantity="2"/>
  <brick elementID="6240206" designID="34823" quantity="6"/>
  <brick elementID="6240379" designID="35164" quantity="2"/>
  <brick elementID="6244911" designID="35743" quantity="2"/>
  <brick elementID="6040339" designID="14137" quantity="3"/>
  <brickCount acquired="84" totalInSet="80"/>
</data>
