<data>
  <brick elementID="9339" designID="73200" quantity="3"/>
  <brick elementID="71155" designID="71155" quantity="1"/>
  <brick elementID="73092" designID="73092" quantity="2"/>
  <brick elementID="73667" designID="73587" quantity="1"/>
  <brick elementID="235726" designID="2357" quantity="4"/>
  <brick elementID="242026" designID="2420" quantity="6"/>
  <brick elementID="255526" designID="2555" quantity="2"/>
  <brick elementID="300126" designID="3001" quantity="1"/>
  <brick elementID="300226" designID="3002" quantity="3"/>
  <brick elementID="300326" designID="3003" quantity="6"/>
  <brick elementID="300526" designID="3005" quantity="2"/>
  <brick elementID="301026" designID="3010" quantity="3"/>
  <brick elementID="302226" designID="3022" quantity="5"/>
  <brick elementID="302326" designID="3023" quantity="12"/>
  <brick elementID="345526" designID="3455" quantity="4"/>
  <brick elementID="348326" designID="3483" quantity="6"/>
  <brick elementID="362226" designID="3622" quantity="2"/>
  <brick elementID="366626" designID="3666" quantity="2"/>
  <brick elementID="370026" designID="3700" quantity="2"/>
  <brick elementID="371026" designID="3710" quantity="10"/>
  <brick elementID="384926" designID="3849" quantity="2"/>
  <brick elementID="394226" designID="3942" quantity="1"/>
  <brick elementID="395826" designID="3958" quantity="1"/>
  <brick elementID="403226" designID="4032" quantity="1"/>
  <brick elementID="407026" designID="4070" quantity="4"/>
  <brick elementID="428226" designID="4282" quantity="1"/>
  <brick elementID="428626" designID="4286" quantity="2"/>
  <brick elementID="452826" designID="4528" quantity="1"/>
  <brick elementID="458926" designID="4589" quantity="10"/>
  <brick elementID="611126" designID="6111" quantity="1"/>
  <brick elementID="614326" designID="6143" quantity="1"/>
  <brick elementID="4105175" designID="3878" quantity="1"/>
  <brick elementID="4107585" designID="30115" quantity="2"/>
  <brick elementID="4109969" designID="30169" quantity="3"/>
  <brick elementID="4113923" designID="30170" quantity="1"/>
  <brick elementID="4617860" designID="92538" quantity="1"/>
  <brick elementID="370826" designID="3708" quantity="1"/>
  <brick elementID="4113951" designID="30156" quantity="2"/>
  <brick elementID="4114053" designID="30136" quantity="15"/>
  <brick elementID="4114055" designID="30137" quantity="12"/>
  <brick elementID="4114064" designID="2454" quantity="2"/>
  <brick elementID="4114306" designID="3003" quantity="4"/>
  <brick elementID="4114312" designID="3298" quantity="2"/>
  <brick elementID="4114319" designID="3001" quantity="2"/>
  <brick elementID="4114322" designID="3039" quantity="12"/>
  <brick elementID="4114324" designID="3460" quantity="1"/>
  <brick elementID="6075179" designID="6112" quantity="3"/>
  <brick elementID="243123" designID="2431" quantity="3"/>
  <brick elementID="303923" designID="3039" quantity="2"/>
  <brick elementID="306923" designID="3069" quantity="1"/>
  <brick elementID="393723" designID="3937" quantity="1"/>
  <brick elementID="486523" designID="4865" quantity="3"/>
  <brick elementID="9342" designID="73200" quantity="1"/>
  <brick elementID="241221" designID="2412" quantity="8"/>
  <brick elementID="243621" designID="2436" quantity="1"/>
  <brick elementID="245021" designID="2450" quantity="4"/>
  <brick elementID="300421" designID="3004" quantity="8"/>
  <brick elementID="302121" designID="3021" quantity="4"/>
  <brick elementID="302221" designID="3022" quantity="2"/>
  <brick elementID="302321" designID="3023" quantity="4"/>
  <brick elementID="306221" designID="3062" quantity="23"/>
  <brick elementID="371021" designID="3710" quantity="1"/>
  <brick elementID="379421" designID="3794" quantity="4"/>
  <brick elementID="613421" designID="6134" quantity="1"/>
  <brick elementID="614121" designID="6141" quantity="10"/>
  <brick elementID="623221" designID="6232" quantity="1"/>
  <brick elementID="4114052" designID="30115" quantity="1"/>
  <brick elementID="4588003" designID="60897" quantity="3"/>
  <brick elementID="242024" designID="2420" quantity="3"/>
  <brick elementID="302024" designID="3020" quantity="4"/>
  <brick elementID="306824" designID="3068" quantity="4"/>
  <brick elementID="362324" designID="3623" quantity="2"/>
  <brick elementID="366624" designID="3666" quantity="1"/>
  <brick elementID="371024" designID="3710" quantity="1"/>
  <brick elementID="379524" designID="3795" quantity="2"/>
  <brick elementID="403224" designID="4032" quantity="3"/>
  <brick elementID="614124" designID="6141" quantity="4"/>
  <brick elementID="74040" designID="73200" quantity="1"/>
  <brick elementID="403228" designID="4032" quantity="2"/>
  <brick elementID="606428" designID="6064" quantity="2"/>
  <brick elementID="346027" designID="3460" quantity="2"/>
  <brick elementID="365927" designID="3659" quantity="2"/>
  <brick elementID="366027" designID="3660" quantity="9"/>
  <brick elementID="384127" designID="3841" quantity="3"/>
  <brick elementID="4105286" designID="30132" quantity="1"/>
  <brick elementID="4106728" designID="30104" quantity="2"/>
  <brick elementID="4110008" designID="3003" quantity="8"/>
  <brick elementID="4113924" designID="30155" quantity="6"/>
  <brick elementID="4113948" designID="30149" quantity="1"/>
  <brick elementID="4113953" designID="30165" quantity="1"/>
  <brick elementID="4114003" designID="3022" quantity="6"/>
  <brick elementID="4114051" designID="30103" quantity="1"/>
  <brick elementID="4114054" designID="30136" quantity="18"/>
  <brick elementID="4114082" designID="3009" quantity="6"/>
  <brick elementID="4114320" designID="3002" quantity="2"/>
  <brick elementID="4114323" designID="3298" quantity="2"/>
  <brick elementID="4114327" designID="6111" quantity="2"/>
  <brick elementID="4113884" designID="6587" quantity="2"/>
  <brick elementID="248925" designID="2489" quantity="1"/>
  <brick elementID="302325" designID="3023" quantity="2"/>
  <brick elementID="9549" designID="73200" quantity="1"/>
  <brick elementID="235702" designID="2357" quantity="6"/>
  <brick elementID="300302" designID="3003" quantity="7"/>
  <brick elementID="300402" designID="3004" quantity="13"/>
  <brick elementID="300502" designID="3005" quantity="2"/>
  <brick elementID="300702" designID="3007" quantity="2"/>
  <brick elementID="300802" designID="3008" quantity="2"/>
  <brick elementID="301002" designID="3010" quantity="7"/>
  <brick elementID="302002" designID="3020" quantity="1"/>
  <brick elementID="302202" designID="3022" quantity="2"/>
  <brick elementID="302302" designID="3023" quantity="10"/>
  <brick elementID="302402" designID="3024" quantity="4"/>
  <brick elementID="303502" designID="3035" quantity="1"/>
  <brick elementID="303602" designID="3036" quantity="1"/>
  <brick elementID="303902" designID="3039" quantity="2"/>
  <brick elementID="306202" designID="3062" quantity="8"/>
  <brick elementID="346002" designID="3460" quantity="2"/>
  <brick elementID="362202" designID="3622" quantity="6"/>
  <brick elementID="362302" designID="3623" quantity="4"/>
  <brick elementID="366602" designID="3666" quantity="2"/>
  <brick elementID="371002" designID="3710" quantity="4"/>
  <brick elementID="393702" designID="3937" quantity="2"/>
  <brick elementID="407002" designID="4070" quantity="1"/>
  <brick elementID="601902" designID="6019" quantity="24"/>
  <brick elementID="4141982" designID="30157" quantity="3"/>
  <brick elementID="4282741" designID="2436" quantity="1"/>
  <brick elementID="4125313" designID="6590" quantity="1"/>
  <brick elementID="4114128" designID="30152" quantity="1"/>
  <brick elementID="4558850" designID="64230" quantity="1"/>
  <brick elementID="70501" designID="70501" quantity="1"/>
  <brick elementID="4113949" designID="30151" quantity="1"/>
  <brick elementID="3005749" designID="30057" quantity="1"/>
  <brick elementID="612647" designID="6126" quantity="4"/>
  <brick elementID="3006848" designID="30068" quantity="2"/>
  <brick elementID="3005741" designID="30057" quantity="2"/>
  <brick elementID="3006841" designID="30068" quantity="4"/>
  <brick elementID="4113954" designID="30153" quantity="1"/>
  <brick elementID="3005744" designID="30057" quantity="2"/>
  <brick elementID="82359" designID="82359" quantity="3"/>
  <brick elementID="371001" designID="3710" quantity="2"/>
  <brick elementID="379501" designID="3795" quantity="2"/>
  <brick elementID="459901" designID="4599" quantity="4"/>
  <brick elementID="626001" designID="6260" quantity="3"/>
  <brick elementID="626501" designID="6265" quantity="6"/>
  <brick elementID="4114328" designID="30136" quantity="4"/>
  <brick elementID="4114329" designID="30137" quantity="1"/>
  <brick elementID="4140583" designID="2540" quantity="1"/>
  <brick elementID="6038450" designID="6266" quantity="6"/>
  <brick elementID="6215045" designID="3895" quantity="1"/>
  <brickCount acquired="530" totalInSet="711"/>
</data>
