<data>
  <brick elementID="237626" designID="2376" quantity="1"/>
  <brick elementID="241226" designID="2412" quantity="1"/>
  <brick elementID="244426" designID="2444" quantity="4"/>
  <brick elementID="244526" designID="2445" quantity="1"/>
  <brick elementID="245426" designID="2454" quantity="4"/>
  <brick elementID="255526" designID="2555" quantity="5"/>
  <brick elementID="265426" designID="2654" quantity="1"/>
  <brick elementID="306226" designID="3062" quantity="4"/>
  <brick elementID="329826" designID="3298" quantity="6"/>
  <brick elementID="370926" designID="3709" quantity="14"/>
  <brick elementID="371026" designID="3710" quantity="9"/>
  <brick elementID="373826" designID="3738" quantity="7"/>
  <brick elementID="379426" designID="3794" quantity="6"/>
  <brick elementID="393826" designID="3938" quantity="2"/>
  <brick elementID="407926" designID="4079" quantity="1"/>
  <brick elementID="409526" designID="4095" quantity="1"/>
  <brick elementID="434926" designID="4349" quantity="5"/>
  <brick elementID="447726" designID="4477" quantity="4"/>
  <brick elementID="458926" designID="4589" quantity="1"/>
  <brick elementID="3003126" designID="30031" quantity="1"/>
  <brick elementID="4107761" designID="32028" quantity="4"/>
  <brick elementID="4143982" designID="30499" quantity="4"/>
  <brick elementID="6021512" designID="42125" quantity="1"/>
  <brick elementID="6208725" designID="30249" quantity="4"/>
  <brick elementID="370526" designID="3705" quantity="12"/>
  <brick elementID="471626" designID="4716" quantity="1"/>
  <brick elementID="4107828" designID="6632" quantity="6"/>
  <brick elementID="4121715" designID="2780" quantity="12"/>
  <brick elementID="4182750" designID="44224" quantity="6"/>
  <brick elementID="4113917" designID="3023" quantity="2"/>
  <brick elementID="4114324" designID="3460" quantity="4"/>
  <brick elementID="4125265" designID="30145" quantity="1"/>
  <brick elementID="4143366" designID="30526" quantity="4"/>
  <brick elementID="4143703" designID="6134" quantity="2"/>
  <brick elementID="4159196" designID="3665" quantity="8"/>
  <brick elementID="4161734" designID="6141" quantity="8"/>
  <brick elementID="4179771" designID="6541" quantity="6"/>
  <brick elementID="4183080" designID="44301" quantity="10"/>
  <brick elementID="4186674" designID="30364" quantity="2"/>
  <brick elementID="302223" designID="3022" quantity="21"/>
  <brick elementID="362323" designID="3623" quantity="10"/>
  <brick elementID="366023" designID="3660" quantity="4"/>
  <brick elementID="370023" designID="3700" quantity="2"/>
  <brick elementID="379523" designID="3795" quantity="3"/>
  <brick elementID="403223" designID="4032" quantity="6"/>
  <brick elementID="407923" designID="4079" quantity="4"/>
  <brick elementID="611223" designID="6112" quantity="4"/>
  <brick elementID="4121925" designID="4460" quantity="2"/>
  <brick elementID="4160391" designID="42022" quantity="2"/>
  <brick elementID="4186666" designID="3455" quantity="2"/>
  <brick elementID="4500125" designID="3069" quantity="4"/>
  <brick elementID="379527" designID="3795" quantity="3"/>
  <brick elementID="3000027" designID="30000" quantity="6"/>
  <brick elementID="4109984" designID="3039" quantity="16"/>
  <brick elementID="4112232" designID="3020" quantity="4"/>
  <brick elementID="4113834" designID="30194" quantity="1"/>
  <brick elementID="4114252" designID="2456" quantity="4"/>
  <brick elementID="4114323" designID="3298" quantity="8"/>
  <brick elementID="4116853" designID="3032" quantity="5"/>
  <brick elementID="4120145" designID="30304" quantity="1"/>
  <brick elementID="4121924" designID="3958" quantity="1"/>
  <brick elementID="4124064" designID="30359" quantity="2"/>
  <brick elementID="4143007" designID="4735" quantity="2"/>
  <brick elementID="4143688" designID="3456" quantity="1"/>
  <brick elementID="4157827" designID="32530" quantity="12"/>
  <brick elementID="4162194" designID="40902" quantity="12"/>
  <brick elementID="4162484" designID="4282" quantity="1"/>
  <brick elementID="4163154" designID="41539" quantity="4"/>
  <brick elementID="4180509" designID="43722" quantity="2"/>
  <brick elementID="4180537" designID="43723" quantity="2"/>
  <brick elementID="4182762" designID="44359" quantity="12"/>
  <brick elementID="4183061" designID="44302" quantity="12"/>
  <brick elementID="4113884" designID="6587" quantity="7"/>
  <brick elementID="302325" designID="3023" quantity="1"/>
  <brick elementID="235702" designID="2357" quantity="2"/>
  <brick elementID="301002" designID="3010" quantity="4"/>
  <brick elementID="303502" designID="3035" quantity="1"/>
  <brick elementID="306202" designID="3062" quantity="1"/>
  <brick elementID="362202" designID="3622" quantity="2"/>
  <brick elementID="366602" designID="3666" quantity="10"/>
  <brick elementID="393702" designID="3937" quantity="4"/>
  <brick elementID="395802" designID="3958" quantity="5"/>
  <brick elementID="408502" designID="4085" quantity="2"/>
  <brick elementID="415002" designID="4150" quantity="2"/>
  <brick elementID="416202" designID="4162" quantity="4"/>
  <brick elementID="458902" designID="4589" quantity="6"/>
  <brick elementID="473302" designID="4733" quantity="1"/>
  <brick elementID="474002" designID="4740" quantity="8"/>
  <brick elementID="610602" designID="6106" quantity="8"/>
  <brick elementID="4107533" designID="3245" quantity="2"/>
  <brick elementID="4113023" designID="2362" quantity="2"/>
  <brick elementID="4117071" designID="32064" quantity="1"/>
  <brick elementID="4118776" designID="30283" quantity="1"/>
  <brick elementID="4121696" designID="30303" quantity="6"/>
  <brick elementID="4124121" designID="30363" quantity="4"/>
  <brick elementID="4140707" designID="30389" quantity="2"/>
  <brick elementID="4142966" designID="30554" quantity="6"/>
  <brick elementID="4160864" designID="41769" quantity="1"/>
  <brick elementID="4161327" designID="41770" quantity="1"/>
  <brick elementID="4177381" designID="42060" quantity="2"/>
  <brick elementID="4182759" designID="44358" quantity="6"/>
  <brick elementID="4185590" designID="44567" quantity="10"/>
  <brick elementID="4186669" designID="3676" quantity="4"/>
  <brick elementID="4186672" designID="4515" quantity="2"/>
  <brick elementID="4187337" designID="44876" quantity="2"/>
  <brick elementID="4234928" designID="43719" quantity="6"/>
  <brick elementID="427402" designID="4274" quantity="6"/>
  <brick elementID="4113804" designID="6538" quantity="1"/>
  <brick elementID="4143020" designID="32524" quantity="4"/>
  <brick elementID="4182580" designID="44225" quantity="6"/>
  <brick elementID="4163155" designID="41862" quantity="1"/>
  <brick elementID="4163457" designID="41747" quantity="1"/>
  <brick elementID="4163459" designID="41748" quantity="1"/>
  <brick elementID="4164220" designID="2431" quantity="1"/>
  <brick elementID="4165435" designID="3839" quantity="1"/>
  <brick elementID="4177047" designID="3021" quantity="2"/>
  <brick elementID="4186696" designID="30259" quantity="2"/>
  <brick elementID="4539097" designID="3023" quantity="28"/>
  <brick elementID="6161299" designID="2453" quantity="2"/>
  <brick elementID="4185942" designID="32557" quantity="4"/>
  <brick elementID="4185944" designID="42610" quantity="1"/>
  <brick elementID="4143269" designID="2412" quantity="1"/>
  <brick elementID="4167490" designID="3068" quantity="11"/>
  <brick elementID="4171688" designID="2540" quantity="1"/>
  <brick elementID="4186359" designID="3001" quantity="2"/>
  <brick elementID="3006840" designID="30068" quantity="1"/>
  <brick elementID="4186673" designID="30007" quantity="2"/>
  <brick elementID="4124073" designID="30374" quantity="1"/>
  <brick elementID="4163917" designID="30057" quantity="4"/>
  <brick elementID="74326" designID="73200" quantity="4"/>
  <brick elementID="4167800" designID="73403" quantity="4"/>
  <brickCount acquired="568" totalInSet="658"/>
</data>
