<data>
  <brick elementID="265426" designID="2654" quantity="4"/>
  <brick elementID="302126" designID="3021" quantity="1"/>
  <brick elementID="302326" designID="3023" quantity="8"/>
  <brick elementID="474026" designID="4740" quantity="1"/>
  <brick elementID="614326" designID="6143" quantity="1"/>
  <brick elementID="4184286" designID="44309" quantity="3"/>
  <brick elementID="4218581" designID="47458" quantity="2"/>
  <brick elementID="4251161" designID="50950" quantity="2"/>
  <brick elementID="4299389" designID="56145" quantity="2"/>
  <brick elementID="4504382" designID="54200" quantity="2"/>
  <brick elementID="4535739" designID="63868" quantity="2"/>
  <brick elementID="4537551" designID="60849" quantity="1"/>
  <brick elementID="4550937" designID="58090" quantity="1"/>
  <brick elementID="4598528" designID="92280" quantity="2"/>
  <brick elementID="4599499" designID="92593" quantity="2"/>
  <brick elementID="6000650" designID="99207" quantity="4"/>
  <brick elementID="6020192" designID="42446" quantity="1"/>
  <brick elementID="6040297" designID="43710" quantity="1"/>
  <brick elementID="6040298" designID="43711" quantity="1"/>
  <brick elementID="6066102" designID="15712" quantity="1"/>
  <brick elementID="6070695" designID="14769" quantity="2"/>
  <brick elementID="6102734" designID="15403" quantity="2"/>
  <brick elementID="6103100" designID="20053" quantity="1"/>
  <brick elementID="6103326" designID="18987" quantity="1"/>
  <brick elementID="6116604" designID="21462" quantity="1"/>
  <brick elementID="6134781" designID="24144" quantity="1"/>
  <brick elementID="6176907" designID="30426" quantity="1"/>
  <brick elementID="4107081" designID="32039" quantity="3"/>
  <brick elementID="4109810" designID="32062" quantity="2"/>
  <brick elementID="4121715" designID="2780" quantity="13"/>
  <brick elementID="4184169" designID="6628" quantity="2"/>
  <brick elementID="4218868" designID="2723" quantity="4"/>
  <brick elementID="6073231" designID="15100" quantity="2"/>
  <brick elementID="6089119" designID="18651" quantity="2"/>
  <brick elementID="6172966" designID="29162" quantity="6"/>
  <brick elementID="6066344" designID="14769" quantity="2"/>
  <brick elementID="4666579" designID="6562" quantity="2"/>
  <brick elementID="302223" designID="3022" quantity="1"/>
  <brick elementID="4140586" designID="2540" quantity="1"/>
  <brick elementID="4496366" designID="47457" quantity="1"/>
  <brick elementID="4543998" designID="50950" quantity="1"/>
  <brick elementID="6143424" designID="47456" quantity="1"/>
  <brick elementID="6145932" designID="26151" quantity="1"/>
  <brick elementID="302221" designID="3022" quantity="1"/>
  <brick elementID="4179355" designID="32000" quantity="2"/>
  <brick elementID="4220515" designID="47457" quantity="1"/>
  <brick elementID="4251162" designID="50950" quantity="1"/>
  <brick elementID="4529234" designID="59900" quantity="1"/>
  <brick elementID="6099736" designID="11458" quantity="2"/>
  <brick elementID="6143425" designID="47456" quantity="1"/>
  <brick elementID="6143426" designID="56145" quantity="1"/>
  <brick elementID="6145893" designID="76382" quantity="1"/>
  <brick elementID="6146110" designID="26168" quantity="1"/>
  <brick elementID="6146185" designID="88585" quantity="1"/>
  <brick elementID="4227155" designID="6590" quantity="3"/>
  <brick elementID="6129995" designID="3705" quantity="2"/>
  <brick elementID="4282745" designID="2436" quantity="2"/>
  <brick elementID="4540384" designID="61409" quantity="2"/>
  <brick elementID="4210700" designID="4733" quantity="1"/>
  <brick elementID="4211039" designID="2432" quantity="1"/>
  <brick elementID="4211043" designID="3021" quantity="2"/>
  <brick elementID="4211065" designID="3020" quantity="2"/>
  <brick elementID="4211079" designID="30192" quantity="1"/>
  <brick elementID="4222693" designID="73200" quantity="1"/>
  <brick elementID="4261908" designID="30031" quantity="2"/>
  <brick elementID="4521187" designID="60478" quantity="1"/>
  <brick elementID="4598769" designID="92593" quantity="2"/>
  <brick elementID="4611703" designID="88072" quantity="1"/>
  <brick elementID="6015890" designID="11090" quantity="2"/>
  <brick elementID="6051334" designID="15392" quantity="3"/>
  <brick elementID="6071261" designID="15068" quantity="1"/>
  <brick elementID="6103106" designID="76382" quantity="1"/>
  <brick elementID="6115080" designID="18674" quantity="1"/>
  <brick elementID="4210686" designID="32316" quantity="3"/>
  <brick elementID="6006141" designID="74695" quantity="2"/>
  <brick elementID="4520632" designID="3001" quantity="2"/>
  <brick elementID="4211353" designID="2420" quantity="2"/>
  <brick elementID="4211395" designID="3020" quantity="1"/>
  <brick elementID="4211397" designID="3022" quantity="1"/>
  <brick elementID="4211412" designID="3062" quantity="2"/>
  <brick elementID="4211441" designID="3701" quantity="3"/>
  <brick elementID="4211475" designID="4032" quantity="2"/>
  <brick elementID="4211525" designID="6141" quantity="5"/>
  <brick elementID="4211658" designID="30377" quantity="1"/>
  <brick elementID="4644102" designID="98397" quantity="1"/>
  <brick elementID="6028812" designID="11476" quantity="1"/>
  <brick elementID="6043639" designID="14418" quantity="2"/>
  <brick elementID="6051333" designID="15391" quantity="1"/>
  <brick elementID="6117967" designID="21712" quantity="4"/>
  <brick elementID="4211508" designID="4697" quantity="1"/>
  <brick elementID="4211573" designID="32123" quantity="2"/>
  <brick elementID="4211865" designID="32054" quantity="6"/>
  <brick elementID="6173127" designID="29219" quantity="2"/>
  <brick elementID="4211166" designID="6143" quantity="2"/>
  <brick elementID="6116613" designID="21462" quantity="1"/>
  <brick elementID="6055631" designID="15462" quantity="3"/>
  <brick elementID="6133263" designID="98721" quantity="1"/>
  <brick elementID="6145948" designID="26156" quantity="1"/>
  <brick elementID="6146098" designID="26167" quantity="1"/>
  <brick elementID="6054858" designID="62462" quantity="4"/>
  <brick elementID="6240030" designID="34823" quantity="2"/>
  <brick elementID="6245250" designID="35338" quantity="1"/>
  <brick elementID="4278409" designID="54196" quantity="1"/>
  <brick elementID="6240227" designID="34823" quantity="6"/>
  <brick elementID="6208450" designID="34823" quantity="4"/>
  <brick elementID="4567332" designID="64288" quantity="2"/>
  <brick elementID="6078364" designID="11090" quantity="1"/>
  <brick elementID="6109685" designID="20896" quantity="1"/>
  <brick elementID="6173139" designID="29175" quantity="4"/>
  <brick elementID="6186672" designID="31561" quantity="4"/>
  <brick elementID="6120936" designID="21955" quantity="1"/>
  <brickCount acquired="223" totalInSet="224"/>
</data>
